birdman/__init__.py
birdman/default_models.py
birdman/diagnostics.py
birdman/model_base.py
birdman/model_util.py
birdman/stats.py
birdman/util.py
birdman/visualization.py
birdman/templates/multinomial.stan
birdman/templates/negative_binomial.stan
birdman/templates/negative_binomial_lme.stan
birdman/templates/negative_binomial_single.stan
tests/__init__.py
tests/conftest.py
tests/custom_model.stan
tests/test_custom_model.py
tests/test_diagnostics.py
tests/test_model.py
tests/test_model_util.py
tests/test_stats.py
tests/test_util.py
tests/test_visualization.py
birdman-0.0.3.dist-info/LICENSE
birdman-0.0.3.dist-info/METADATA
birdman-0.0.3.dist-info/WHEEL
birdman-0.0.3.dist-info/top_level.txt
birdman-0.0.3.dist-info/RECORD
