Metadata-Version: 2.1
Name: birdman
Version: 0.0.3
Summary: Framework for differential microbiome abundance using Bayesian inference
Home-page: https://github.com/gibsramen/BIRDMAn
Author: Gibraan Rahman
Author-email: grahman@eng.ucsd.edu
License: BSD-3-Clause
Platform: UNKNOWN
Classifier: Development Status :: 3 - Alpha
Classifier: License :: OSI Approved :: BSD License
Classifier: Programming Language :: Python :: 3.7
Classifier: Programming Language :: Python :: 3.8
Classifier: Programming Language :: Python :: 3.9
Classifier: Intended Audience :: Science/Research
Classifier: Operating System :: POSIX
Classifier: Operating System :: MacOS :: MacOS X
Classifier: Topic :: Scientific/Engineering :: Bio-Informatics
License-File: LICENSE
Requires-Dist: numpy
Requires-Dist: cmdstanpy
Requires-Dist: dask[complete]
Requires-Dist: biom-format
Requires-Dist: patsy
Requires-Dist: xarray
Requires-Dist: pandas
Requires-Dist: arviz
Provides-Extra: dev
Requires-Dist: pytest ; extra == 'dev'
Requires-Dist: scikit-bio ; extra == 'dev'
Requires-Dist: sphinx ; extra == 'dev'
